pashehnet/__init__.py
pashehnet/cli.py
pashehnet/network/__init__.py
pashehnet/network/network.py
pashehnet/sensors/__init__.py
pashehnet/sensors/helpers.py
pashehnet/sensors/sensor.py
pashehnet/sensors/formats/__init__.py
pashehnet/sensors/formats/base.py
pashehnet/sensors/formats/csv.py
pashehnet/sensors/formats/json.py
pashehnet/sensors/formats/simple.py
pashehnet/sensors/formats/string.py
pashehnet/sensors/sources/__init__.py
pashehnet/sensors/sources/base.py
pashehnet/sensors/sources/chirp.py
pashehnet/sensors/sources/constant.py
pashehnet/sensors/sources/file.py
pashehnet/sensors/sources/gaussianpulse.py
pashehnet/sensors/sources/sawtoothwave.py
pashehnet/sensors/sources/series.py
pashehnet/sensors/sources/squarewave.py
pashehnet/sensors/sources/sweep_poly.py
pashehnet/sensors/sources/unit_impulse.py
pashehnet/sensors/transforms/__init__.py
pashehnet/sensors/transforms/base.py
pashehnet/sensors/transforms/dropout.py
pashehnet/sensors/transforms/stuck.py
pashehnet/targets/__init__.py
pashehnet/targets/base.py
pashehnet/targets/mqtt.py
pashehnet-0.1.1.dist-info/LICENSE
pashehnet-0.1.1.dist-info/METADATA
pashehnet-0.1.1.dist-info/WHEEL
pashehnet-0.1.1.dist-info/entry_points.txt
pashehnet-0.1.1.dist-info/top_level.txt
pashehnet-0.1.1.dist-info/RECORD
