Metadata-Version: 2.1
Name: pashehnet
Version: 0.1.1
Summary: Sensor network simulator publishing to MQTT broker
Author-email: Robert Bates <rbates@zaggy.ai>
Project-URL: Homepage, https://github.com/zaggyai/pashehnet
Project-URL: Source, https://github.com/zaggyai/pashehnet
Project-URL: Documentation, https://pashehnet.readthedocs.io
Project-URL: Bug Tracker, https://github.com/zaggyai/pashehnet/issues
Classifier: Programming Language :: Python :: 3
Classifier: License :: OSI Approved :: MIT License
Classifier: Operating System :: OS Independent
Requires-Python: >=3.8
License-File: LICENSE
Requires-Dist: paho-mqtt ~=1.6
Requires-Dist: envyaml ~=1.10
Requires-Dist: fire ~=0.5
Requires-Dist: scipy ~=1.10
Requires-Dist: smart-open ~=6.4
Requires-Dist: pandas ~=2.0
Requires-Dist: jsonpath-ng ~=1.6
Requires-Dist: schema ~=0.7
